fastapi_auto_restful/__init__.py
fastapi_auto_restful/auto_router.py
fastapi_auto_restful/query_parser.py
fastapi_auto_restful/schemas.py
fastapi_auto_restful-0.3.1.dist-info/licenses/LICENSE
fastapi_auto_restful-0.3.1.dist-info/METADATA
fastapi_auto_restful-0.3.1.dist-info/WHEEL
fastapi_auto_restful-0.3.1.dist-info/top_level.txt
fastapi_auto_restful-0.3.1.dist-info/RECORD
